wrmodes/__init__.py
wrmodes/main.py
wrmodes/mode_coupling.py
wrmodes-0.0.5.dist-info/METADATA
wrmodes-0.0.5.dist-info/WHEEL
wrmodes-0.0.5.dist-info/entry_points.txt
wrmodes-0.0.5.dist-info/licenses/LICENSE
wrmodes-0.0.5.dist-info/RECORD
